{
  "extracted_values": {
    "Source_Document_Title": "CREDIT AGREEMENT",
    "LegalIssuer": [
      "Capstone Borrower, Inc."
    ],
    "Sponsor_name": [
      "the Blackstone Funds"
    ],
    "MostRecentDocDate": "05/18/2023",
    "Administrative_Agent": [
      "MORGAN STANLEY SENIOR FUNDING, INC."
    ],
    "Lead_Arrangers": [
      "MORGAN STANLEY SENIOR FUNDING, INC.",
      "UBS SECURITIES LLC",
      "CITIZENS BANK, N.A.",
      "FIFTH THIRD BANK, NATIONAL ASSOCIATION"
    ],
    "AmendmentNumber": "NOT SPECIFIED"
  },
  "metadata_mapping": {
    "Source_Document_Title": [
      {
        "value": "CREDIT AGREEMENT",
        "page": 1,
        "block_id": 3,
        "bbox": {
          "x0": 255.88999938964844,
          "y0": 114.98562622070312,
          "x1": 358.7200012207031,
          "y1": 126.01134490966797
        },
        "page_width": 612.0,
        "page_height": 792.0
      }
    ],
    "LegalIssuer": [
      {
        "value": "Capstone Borrower, Inc.",
        "page": 1,
        "block_id": 3,
        "bbox": {
          "x0": 255.88999938964844,
          "y0": 114.98562622070312,
          "x1": 358.7200012207031,
          "y1": 126.01134490966797
        },
        "page_width": 612.0,
        "page_height": 792.0
      }
    ],
    "Sponsor_name": [
      {
        "value": "the Blackstone Funds",
        "page": 72,
        "block_id": 15,
        "bbox": {
          "x0": 72.02400207519531,
          "y0": 550.03564453125,
          "x1": 542.4035034179688,
          "y1": 572.5813598632812
        },
        "page_width": 612.0,
        "page_height": 792.0
      }
    ],
    "MostRecentDocDate": [
      {
        "value": "MAY 18, 2023",
        "page": 1,
        "block_id": 0,
        "bbox": {
          "x0": 446.95001220703125,
          "y0": 54.485626220703125,
          "x1": 542.5899658203125,
          "y1": 65.51134490966797
        },
        "page_width": 612.0,
        "page_height": 792.0
      }
    ],
    "Administrative_Agent": [
      {
        "value": "MORGAN STANLEY SENIOR FUNDING, INC.",
        "page": 1,
        "block_id": 9,
        "bbox": {
          "x0": 142.4600067138672,
          "y0": 241.97561645507812,
          "x1": 472.1499938964844,
          "y1": 276.0413818359375
        },
        "page_width": 612.0,
        "page_height": 792.0
      }
    ],
    "Lead_Arrangers": [
      {
        "value": "MORGAN STANLEY SENIOR FUNDING, INC.",
        "page": 1,
        "block_id": 11,
        "bbox": {
          "x0": 203.08999633789062,
          "y0": 299.45562744140625,
          "x1": 411.5199890136719,
          "y1": 322.0013732910156
        },
        "page_width": 612.0,
        "page_height": 792.0
      },
      {
        "value": "UBS SECURITIES LLC",
        "page": 1,
        "block_id": 11,
        "bbox": {
          "x0": 203.08999633789062,
          "y0": 299.45562744140625,
          "x1": 411.5199890136719,
          "y1": 322.0013732910156
        },
        "page_width": 612.0,
        "page_height": 792.0
      },
      {
        "value": "CITIZENS BANK, N.A.",
        "page": 1,
        "block_id": 11,
        "bbox": {
          "x0": 203.08999633789062,
          "y0": 299.45562744140625,
          "x1": 411.5199890136719,
          "y1": 322.0013732910156
        },
        "page_width": 612.0,
        "page_height": 792.0
      },
      {
        "value": "FIFTH THIRD BANK, NATIONAL ASSOCIATION",
        "page": 1,
        "block_id": 11,
        "bbox": {
          "x0": 203.08999633789062,
          "y0": 299.45562744140625,
          "x1": 411.5199890136719,
          "y1": 322.0013732910156
        },
        "page_width": 612.0,
        "page_height": 792.0
      }
    ],
    "AmendmentNumber": []
  }
}